{"version":1,"resource":"file:///home/dmarkovic/Downloads/ansible-k3s/roles/install-wordpress/templates/values.yaml.j2","entries":[{"id":"mxnE.j2","timestamp":1743535052164},{"id":"pKYu.j2","timestamp":1743535115981},{"id":"ae7J.j2","timestamp":1743535180874},{"id":"ghKc.j2","timestamp":1743535246180},{"id":"joJz.j2","timestamp":1743535460403},{"id":"hKGH.j2","timestamp":1743536691874},{"id":"I0Qu.j2","timestamp":1743536745257},{"id":"vwxP.j2","timestamp":1743536799607},{"id":"bQud.j2","timestamp":1743536882341},{"id":"Fp3C.j2","timestamp":1743536918292},{"id":"JLMW.j2","timestamp":1743537113485},{"id":"TeeC.j2","timestamp":1743587095944},{"id":"UKye.j2","timestamp":1743588923335},{"id":"a8UI.j2","timestamp":1743598064439},{"id":"Iuz7.j2","timestamp":1743598096619},{"id":"vblM.j2","timestamp":1743598174002},{"id":"W4Bs.j2","timestamp":1743599514775},{"id":"MOt4.j2","timestamp":1743845529180},{"id":"nmcu.j2","timestamp":1743846678489},{"id":"lbJg.j2","timestamp":1743857618575},{"id":"3cQY.j2","timestamp":1743857634982}]}