{"version":1,"resource":"file:///home/dmarkovic/Documents/cluster-configuration/.gitignore","entries":[{"id":"gIy7","timestamp":1740056003165},{"id":"5P6D","timestamp":1740056046796},{"id":"DDFx","timestamp":1740056103497},{"id":"MjUk","timestamp":1741098418507},{"id":"qtDT","timestamp":1742473553975},{"id":"vjyG","timestamp":1742473600218},{"id":"Lz5Q","timestamp":1742474782138},{"id":"Qsof","timestamp":1742474798823},{"id":"l19c","timestamp":1742474813154},{"id":"DyO2","timestamp":1742474862772},{"id":"Uask","timestamp":1742474894047},{"id":"Xidq","timestamp":1742474913538},{"id":"MNBD","timestamp":1742474970303},{"id":"DAik","timestamp":1742476143899},{"id":"5kC5","timestamp":1742477871485}]}