{"version":1,"resource":"file:///home/dmarkovic/git-projects/publicplan/wsp/app-configs/applications/govforms2-workflow-core/base/rabbitmq/rabbitmq.yaml","entries":[{"id":"jO1R.yaml","timestamp":1730895184521},{"id":"sVIw.yaml","timestamp":1730895222458},{"id":"hzrb.yaml","timestamp":1730895380578},{"id":"LdBa.yaml","timestamp":1730895478908},{"id":"HjrH.yaml","timestamp":1730896520022},{"id":"U9hc.yaml","timestamp":1730896539152},{"id":"AbTD.yaml","source":"undoRedo.source","timestamp":1730896542319},{"id":"r86E.yaml","timestamp":1730896554506},{"id":"SitB.yaml","timestamp":1730972306775},{"id":"yvHW.yaml","timestamp":1731586409999}]}