{"version":1,"resource":"file:///home/dmarkovic/git-projects/publicplan/fmth-formsflow-docker-config/forms-flow-idm-keycloak/forms-flow-idm-keycloak-compose.yml","entries":[{"id":"5wD0.yml","timestamp":1711354791599},{"id":"MVVH.yml","timestamp":1711354863970},{"id":"FtVb.yml","timestamp":1711446701137},{"id":"HDW4.yml","timestamp":1711446728304},{"id":"VAtR.yml","timestamp":1711447811604},{"id":"9Q52.yml","timestamp":1711447822260},{"id":"XxKr.yml","timestamp":1711450415358},{"id":"kXg5.yml","timestamp":1711450515518},{"id":"cpCE.yml","timestamp":1711450587138},{"id":"Xbjc.yml","timestamp":1711450641434},{"id":"14P9.yml","timestamp":1711456064294},{"id":"SBEv.yml","timestamp":1711456226843},{"id":"aGTg.yml","timestamp":1711456325773},{"id":"nIFs.yml","timestamp":1711456394376},{"id":"Ugju.yml","timestamp":1711457141658},{"id":"eDRS.yml","timestamp":1711457374204},{"id":"9Zdh.yml","timestamp":1711459586439},{"id":"qvSy.yml","source":"searchReplace.source","timestamp":1712136672928},{"id":"QWKe.yml","timestamp":1712136808585},{"id":"ciAq.yml","source":"searchReplace.source","timestamp":1712136910768},{"id":"6mi2.yml","timestamp":1712148349559},{"id":"wT54.yml","source":"undoRedo.source","timestamp":1712150449283},{"id":"6BLe.yml","timestamp":1712150452293},{"id":"6iVw.yml","timestamp":1712221547588},{"id":"Civi.yml","timestamp":1712226232806},{"id":"PJqM.yml","timestamp":1712226908442},{"id":"nWTY.yml","timestamp":1713524356808},{"id":"oEGH.yml","timestamp":1713527927098}]}